parthsql/__init__.py
parthsql/main.py
parthsql/parthsql.py
parthsql-1.2.0.dist-info/DESCRIPTION.rst
parthsql-1.2.0.dist-info/METADATA
parthsql-1.2.0.dist-info/RECORD
parthsql-1.2.0.dist-info/WHEEL
parthsql-1.2.0.dist-info/entry_points.txt
parthsql-1.2.0.dist-info/metadata.json
parthsql-1.2.0.dist-info/top_level.txt
