Metadata-Version: 2.0
Name: parthsql
Version: 1.2.0
Summary: A mini SQL query engine written in Python
Home-page: https://github.com/ParthKolekar/parthsql
Author: Parth Kolekar
Author-email: parth.kolekar@students.iiit.ac.in
License: ISCL
Keywords: parthsql
Platform: UNKNOWN
Classifier: Development Status :: 2 - Pre-Alpha
Classifier: Intended Audience :: Developers
Classifier: License :: OSI Approved :: ISC License (ISCL)
Classifier: Natural Language :: English
Classifier: Programming Language :: Python :: 2
Classifier: Programming Language :: Python :: 2.7
Requires-Dist: sqlparse (==0.1.18)
